testery.py
tests/__init__.py
tests/conftest.py
tests/test_integration.py
tests/test_unit.py
testery-1.13.3.dist-info/LICENSE
testery-1.13.3.dist-info/METADATA
testery-1.13.3.dist-info/WHEEL
testery-1.13.3.dist-info/entry_points.txt
testery-1.13.3.dist-info/top_level.txt
testery-1.13.3.dist-info/RECORD
