Metadata-Version: 2.1
Name: testery
Version: 1.13.3
Summary: Testery CLI
Home-page: https://github.com/testery/testery-cli
Author: Testery
Author-email: chris.harbert@testery.io
License: UNKNOWN
Platform: UNKNOWN
Classifier: Programming Language :: Python :: 3
Classifier: License :: OSI Approved :: MIT License
Classifier: Operating System :: OS Independent
Requires-Dist: Click
Requires-Dist: python-dateutil
Requires-Dist: python-dotenv
Requires-Dist: requests
Requires-Dist: requests-toolbelt
